termdown.py
termdown-1.18.0.dist-info/AUTHORS
termdown-1.18.0.dist-info/LICENSE
termdown-1.18.0.dist-info/METADATA
termdown-1.18.0.dist-info/WHEEL
termdown-1.18.0.dist-info/entry_points.txt
termdown-1.18.0.dist-info/top_level.txt
termdown-1.18.0.dist-info/RECORD
