Metadata-Version: 2.1
Name: termdown
Version: 1.18.0
Summary: Countdown timer for your terminal
Home-page: https://github.com/trehn/termdown
Author: Torsten Rehn
Author-email: torsten@rehn.email
License: GPLv3
Keywords: console,countdown,curses,stopwatch,terminal,timer
Platform: UNKNOWN
Classifier: Development Status :: 5 - Production/Stable
Classifier: Environment :: Console :: Curses
Classifier: License :: OSI Approved :: GNU General Public License v3 (GPLv3)
Classifier: Natural Language :: English
Classifier: Operating System :: MacOS :: MacOS X
Classifier: Operating System :: POSIX
Classifier: Operating System :: Unix
Classifier: Programming Language :: Python :: 3
Classifier: Topic :: Utilities
License-File: LICENSE
License-File: AUTHORS
Requires-Dist: click (>=2.0)
Requires-Dist: pyfiglet (>=0.7)
Requires-Dist: python-dateutil
Requires-Dist: windows-curses ; platform_system == "Windows"
